Compiled from "Main.java"
public class Main implements java.lang.Runnable {
  private final java.lang.Object obj;

  private static final java.lang.Object oObj;

  private static final boolean zObj;

  private static final byte bObj;

  private static final short sObj;

  private static final int iObj;

  private static final float fObj;

  private static final long jObj;

  private static final double dObj;

  private static final java.lang.String strObj;

  private static final java.lang.Class<?> clz;

  public Main();
    Code:
       0: aload_0
       1: invokespecial #1                  // Method java/lang/Object."<init>":()V
       4: aload_0
       5: ldc           #2                  // class Main
       7: putfield      #3                  // Field obj:Ljava/lang/Object;
      10: return

  public static void main(java.lang.String[]) throws java.lang.Exception;
    Code:
       0: getstatic     #4                  // Field java/lang/System.out:Ljava/io/PrintStream;
       3: ldc           #5                  // String Hello, world !
       5: invokevirtual #6                  // Method java/io/PrintStream.println:(Ljava/lang/String;)V
       8: return

  public final void run();
    Code:
       0: return

  private static int C(int, int);
    Code:
       0: fconst_1
       1: fstore_2
       2: iconst_0
       3: istore_3
       4: iload_3
       5: iload_1
       6: if_icmpge     22
       9: fload_2
      10: iload_0
      11: iload_3
      12: isub
      13: i2f
      14: fmul
      15: fstore_2
      16: iinc          3, 1
      19: goto          4
      22: iconst_2
      23: istore_3
      24: iload_3
      25: iload_1
      26: if_icmpgt     40
      29: fload_2
      30: iload_3
      31: i2f
      32: fdiv
      33: fstore_2
      34: iinc          3, 1
      37: goto          24
      40: fload_2
      41: ldc           #7                  // float 0.5f
      43: fadd
      44: f2i
      45: ireturn

  public static void qsort(int[], int, int);
    Code:
       0: iload_1
       1: iload_2
       2: if_icmplt     6
       5: return
       6: iload_1
       7: istore_3
       8: iload_2
       9: istore        4
      11: aload_0
      12: iload_3
      13: iaload
      14: istore        5
      16: iload         4
      18: iload_3
      19: if_icmple     37
      22: aload_0
      23: iload         4
      25: iaload
      26: iload         5
      28: if_icmplt     37
      31: iinc          4, -1
      34: goto          16
      37: iload         4
      39: iload_3
      40: if_icmpne     46
      43: goto          98
      46: aload_0
      47: iload_3
      48: iinc          3, 1
      51: aload_0
      52: iload         4
      54: iaload
      55: iastore
      56: iload         4
      58: iload_3
      59: if_icmple     76
      62: aload_0
      63: iload_3
      64: iaload
      65: iload         5
      67: if_icmpgt     76
      70: iinc          3, 1
      73: goto          56
      76: iload         4
      78: iload_3
      79: if_icmpne     85
      82: goto          98
      85: aload_0
      86: iload         4
      88: iinc          4, -1
      91: aload_0
      92: iload_3
      93: iaload
      94: iastore
      95: goto          16
      98: aload_0
      99: iload_3
     100: iload         5
     102: iastore
     103: aload_0
     104: iload_1
     105: iload_3
     106: iconst_1
     107: isub
     108: invokestatic  #8                  // Method qsort:([III)V
     111: aload_0
     112: iload_3
     113: iconst_1
     114: iadd
     115: iload_2
     116: invokestatic  #8                  // Method qsort:([III)V
     119: return

  public static void msort(int[], int, int, int[]);
    Code:
       0: iload_1
       1: iload_2
       2: if_icmplt     6
       5: return
       6: aload_3
       7: ifnonnull     15
      10: aload_0
      11: arraylength
      12: newarray       int
      14: astore_3
      15: iload_1
      16: iload_2
      17: iadd
      18: iconst_2
      19: idiv
      20: istore        4
      22: aload_0
      23: iload_1
      24: iload         4
      26: aload_3
      27: invokestatic  #9                  // Method msort:([III[I)V
      30: aload_0
      31: iload         4
      33: iconst_1
      34: iadd
      35: iload_2
      36: aload_3
      37: invokestatic  #9                  // Method msort:([III[I)V
      40: iload_1
      41: istore        5
      43: iload         4
      45: iconst_1
      46: iadd
      47: istore        6
      49: iconst_0
      50: istore        7
      52: iload         5
      54: iload         4
      56: if_icmpgt     103
      59: iload         6
      61: iload_2
      62: if_icmpgt     103
      65: aload_3
      66: iload         7
      68: iinc          7, 1
      71: aload_0
      72: iload         5
      74: iaload
      75: aload_0
      76: iload         6
      78: iaload
      79: if_icmpge     92
      82: aload_0
      83: iload         5
      85: iinc          5, 1
      88: iaload
      89: goto          99
      92: aload_0
      93: iload         6
      95: iinc          6, 1
      98: iaload
      99: iastore
     100: goto          52
     103: iload         5
     105: iload         4
     107: if_icmpgt     127
     110: aload_3
     111: iload         7
     113: iinc          7, 1
     116: aload_0
     117: iload         5
     119: iinc          5, 1
     122: iaload
     123: iastore
     124: goto          103
     127: iload         6
     129: iload_2
     130: if_icmpgt     150
     133: aload_3
     134: iload         7
     136: iinc          7, 1
     139: aload_0
     140: iload         6
     142: iinc          6, 1
     145: iaload
     146: iastore
     147: goto          127
     150: iconst_0
     151: istore        7
     153: iload_1
     154: iload_2
     155: if_icmpgt     174
     158: aload_0
     159: iload_1
     160: iinc          1, 1
     163: aload_3
     164: iload         7
     166: iinc          7, 1
     169: iaload
     170: iastore
     171: goto          153
     174: return

  public static java.lang.String open(java.lang.String) throws java.io.IOException;
    Code:
       0: new           #10                 // class java/io/File
       3: dup
       4: aload_0
       5: invokespecial #11                 // Method java/io/File."<init>":(Ljava/lang/String;)V
       8: astore_1
       9: new           #12                 // class java/io/StringWriter
      12: dup
      13: aload_1
      14: invokevirtual #13                 // Method java/io/File.length:()J
      17: l2i
      18: invokespecial #14                 // Method java/io/StringWriter."<init>":(I)V
      21: astore_2
      22: new           #15                 // class java/io/FileReader
      25: dup
      26: aload_1
      27: invokespecial #16                 // Method java/io/FileReader."<init>":(Ljava/io/File;)V
      30: astore_3
      31: sipush        4096
      34: newarray       char
      36: astore        4
      38: aload_3
      39: aload         4
      41: invokevirtual #17                 // Method java/io/FileReader.read:([C)I
      44: dup
      45: istore        5
      47: iconst_m1
      48: if_icmpeq     63
      51: aload_2
      52: aload         4
      54: iconst_0
      55: iload         5
      57: invokevirtual #18                 // Method java/io/StringWriter.write:([CII)V
      60: goto          38
      63: aload_2
      64: invokevirtual #19                 // Method java/io/StringWriter.flush:()V
      67: aload_2
      68: invokevirtual #20                 // Method java/io/StringWriter.close:()V
      71: aload_3
      72: invokevirtual #21                 // Method java/io/FileReader.close:()V
      75: aload_2
      76: invokevirtual #22                 // Method java/io/StringWriter.toString:()Ljava/lang/String;
      79: areturn

  static {};
    Code:
       0: ldc           #2                  // class Main
       2: putstatic     #23                 // Field oObj:Ljava/lang/Object;
       5: ldc           #24                 // class java/lang/String
       7: putstatic     #25                 // Field clz:Ljava/lang/Class;
      10: return
}
